{
  "title": "Santo pra Sempre",
  "artist": "Gabriel Guedes",
  "link": "https://www.youtube.com/watch?v=ijNCc7ICCck",
  "tempo": {
    "note": "quarter",
    "bpm": 72
  },
  "musicXML": "<?xml version=\"1.0\" encoding=\"UTF-8\"?>\n<!DOCTYPE score-partwise PUBLIC \"-//Recordare//DTD MusicXML 4.0 Partwise//EN\" \"http://www.musicxml.org/dtds/partwise.dtd\">\n<score-partwise version=\"4.0\">\n  <work>\n    <work-title>Partitura sem título</work-title>\n    </work>\n  <identification>\n    <creator type=\"composer\">Compositor / arranjador</creator>\n    <encoding>\n      <software>MuseScore Studio 4.7.3</software>\n      <encoding-date>2026-06-30</encoding-date>\n      <supports element=\"accidental\" type=\"yes\"/>\n      <supports element=\"beam\" type=\"yes\"/>\n      <supports element=\"print\" attribute=\"new-page\" type=\"no\"/>\n      <supports element=\"print\" attribute=\"new-system\" type=\"no\"/>\n      <supports element=\"stem\" type=\"yes\"/>\n      </encoding>\n    <miscellaneous>\n      <miscellaneous-field name=\"creationDate\">2026-06-27</miscellaneous-field>\n      <miscellaneous-field name=\"platform\">Microsoft Windows</miscellaneous-field>\n      </miscellaneous>\n    </identification>\n  <part-list>\n    <score-part id=\"P1\">\n      <part-name print-object=\"no\">Bateria</part-name>\n      <part-abbreviation print-object=\"no\">Bta.</part-abbreviation>\n      <score-instrument id=\"P1-I1\">\n        <instrument-name>Snare Ghost Note</instrument-name>\n        </score-instrument>\n      <score-instrument id=\"P1-I36\">\n        <instrument-name>Bass Drum 2</instrument-name>\n        </score-instrument>\n      <score-instrument id=\"P1-I37\">\n        <instrument-name>Bass Drum</instrument-name>\n        </score-instrument>\n      <score-instrument id=\"P1-I38\">\n        <instrument-name>Cross-stick</instrument-name>\n        </score-instrument>\n      <score-instrument id=\"P1-I39\">\n        <instrument-name>Snare</instrument-name>\n        </score-instrument>\n      <score-instrument id=\"P1-I42\">\n        <instrument-name>Floor Tom</instrument-name>\n        </score-instrument>\n      <score-instrument id=\"P1-I43\">\n        <instrument-name>Chimbal fechado</instrument-name>\n        </score-instrument>\n      <score-instrument id=\"P1-I45\">\n        <instrument-name>Pedal de chimbal</instrument-name>\n        </score-instrument>\n      <score-instrument id=\"P1-I47\">\n        <instrument-name>Open Hi-Hat</instrument-name>\n        </score-instrument>\n      <score-instrument id=\"P1-I48\">\n        <instrument-name>Low Tom</instrument-name>\n        </score-instrument>\n      <score-instrument id=\"P1-I50\">\n        <instrument-name>Crash Cymbal</instrument-name>\n        </score-instrument>\n      <score-instrument id=\"P1-I51\">\n        <instrument-name>High Tom</instrument-name>\n        </score-instrument>\n      <score-instrument id=\"P1-I52\">\n        <instrument-name>Ride Cymbal</instrument-name>\n        </score-instrument>\n      <score-instrument id=\"P1-I53\">\n        <instrument-name>China Cymbal</instrument-name>\n        </score-instrument>\n      <score-instrument id=\"P1-I54\">\n        <instrument-name>Ride Bell</instrument-name>\n        </score-instrument>\n      <score-instrument id=\"P1-I56\">\n        <instrument-name>Splash Cymbal</instrument-name>\n        </score-instrument>\n      <score-instrument id=\"P1-I58\">\n        <instrument-name>Crash Cymbal 2</instrument-name>\n        </score-instrument>\n      <midi-device port=\"1\"></midi-device>\n      <midi-instrument id=\"P1-I1\">\n        <midi-channel>10</midi-channel>\n        <midi-program>1</midi-program>\n        <midi-unpitched>1</midi-unpitched>\n        <volume>78.7402</volume>\n        <pan>0</pan>\n        </midi-instrument>\n      <midi-instrument id=\"P1-I36\">\n        <midi-channel>10</midi-channel>\n        <midi-program>1</midi-program>\n        <midi-unpitched>36</midi-unpitched>\n        <volume>78.7402</volume>\n        <pan>0</pan>\n        </midi-instrument>\n      <midi-instrument id=\"P1-I37\">\n        <midi-channel>10</midi-channel>\n        <midi-program>1</midi-program>\n        <midi-unpitched>37</midi-unpitched>\n        <volume>78.7402</volume>\n        <pan>0</pan>\n        </midi-instrument>\n      <midi-instrument id=\"P1-I38\">\n        <midi-channel>10</midi-channel>\n        <midi-program>1</midi-program>\n        <midi-unpitched>38</midi-unpitched>\n        <volume>78.7402</volume>\n        <pan>0</pan>\n        </midi-instrument>\n      <midi-instrument id=\"P1-I39\">\n        <midi-channel>10</midi-channel>\n        <midi-program>1</midi-program>\n        <midi-unpitched>39</midi-unpitched>\n        <volume>78.7402</volume>\n        <pan>0</pan>\n        </midi-instrument>\n      <midi-instrument id=\"P1-I42\">\n        <midi-channel>10</midi-channel>\n        <midi-program>1</midi-program>\n        <midi-unpitched>42</midi-unpitched>\n        <volume>78.7402</volume>\n        <pan>0</pan>\n        </midi-instrument>\n      <midi-instrument id=\"P1-I43\">\n        <midi-channel>10</midi-channel>\n        <midi-program>1</midi-program>\n        <midi-unpitched>43</midi-unpitched>\n        <volume>78.7402</volume>\n        <pan>0</pan>\n        </midi-instrument>\n      <midi-instrument id=\"P1-I45\">\n        <midi-channel>10</midi-channel>\n        <midi-program>1</midi-program>\n        <midi-unpitched>45</midi-unpitched>\n        <volume>78.7402</volume>\n        <pan>0</pan>\n        </midi-instrument>\n      <midi-instrument id=\"P1-I47\">\n        <midi-channel>10</midi-channel>\n        <midi-program>1</midi-program>\n        <midi-unpitched>47</midi-unpitched>\n        <volume>78.7402</volume>\n        <pan>0</pan>\n        </midi-instrument>\n      <midi-instrument id=\"P1-I48\">\n        <midi-channel>10</midi-channel>\n        <midi-program>1</midi-program>\n        <midi-unpitched>48</midi-unpitched>\n        <volume>78.7402</volume>\n        <pan>0</pan>\n        </midi-instrument>\n      <midi-instrument id=\"P1-I50\">\n        <midi-channel>10</midi-channel>\n        <midi-program>1</midi-program>\n        <midi-unpitched>50</midi-unpitched>\n        <volume>78.7402</volume>\n        <pan>0</pan>\n        </midi-instrument>\n      <midi-instrument id=\"P1-I51\">\n        <midi-channel>10</midi-channel>\n        <midi-program>1</midi-program>\n        <midi-unpitched>51</midi-unpitched>\n        <volume>78.7402</volume>\n        <pan>0</pan>\n        </midi-instrument>\n      <midi-instrument id=\"P1-I52\">\n        <midi-channel>10</midi-channel>\n        <midi-program>1</midi-program>\n        <midi-unpitched>52</midi-unpitched>\n        <volume>78.7402</volume>\n        <pan>0</pan>\n        </midi-instrument>\n      <midi-instrument id=\"P1-I53\">\n        <midi-channel>10</midi-channel>\n        <midi-program>1</midi-program>\n        <midi-unpitched>53</midi-unpitched>\n        <volume>78.7402</volume>\n        <pan>0</pan>\n        </midi-instrument>\n      <midi-instrument id=\"P1-I54\">\n        <midi-channel>10</midi-channel>\n        <midi-program>1</midi-program>\n        <midi-unpitched>54</midi-unpitched>\n        <volume>78.7402</volume>\n        <pan>0</pan>\n        </midi-instrument>\n      <midi-instrument id=\"P1-I56\">\n        <midi-channel>10</midi-channel>\n        <midi-program>1</midi-program>\n        <midi-unpitched>56</midi-unpitched>\n        <volume>78.7402</volume>\n        <pan>0</pan>\n        </midi-instrument>\n      <midi-instrument id=\"P1-I58\">\n        <midi-channel>10</midi-channel>\n        <midi-program>1</midi-program>\n        <midi-unpitched>58</midi-unpitched>\n        <volume>78.7402</volume>\n        <pan>0</pan>\n        </midi-instrument>\n      </score-part>\n    </part-list>\n  <part id=\"P1\">\n    <measure number=\"1\">\n      <attributes>\n        <divisions>24</divisions>\n        <key>\n          <fifths>0</fifths>\n          <mode>none</mode>\n          </key>\n        <time>\n          <beats>4</beats>\n          <beat-type>4</beat-type>\n          </time>\n        <clef>\n          <sign>percussion</sign>\n          </clef>\n        </attributes>\n      <direction placement=\"above\" system=\"only-top\">\n        <direction-type>\n          <metronome parentheses=\"no\">\n            <beat-unit>quarter</beat-unit>\n            <per-minute>72</per-minute>\n            </metronome>\n          </direction-type>\n        <sound tempo=\"72\"/>\n        </direction>\n      <note>\n        <rest measure=\"yes\"/>\n        <duration>96</duration>\n        <voice>1</voice>\n        </note>\n      </measure>\n    <measure number=\"2\">\n      <note>\n        <rest measure=\"yes\"/>\n        <duration>96</duration>\n        <voice>1</voice>\n        </note>\n      </measure>\n    <measure number=\"3\">\n      <note>\n        <rest/>\n        <duration>48</duration>\n        <voice>1</voice>\n        <type>half</type>\n        </note>\n      <note>\n        <rest/>\n        <duration>24</duration>\n        <voice>1</voice>\n        <type>quarter</type>\n        </note>\n      <direction placement=\"below\">\n        <direction-type>\n          <wedge type=\"crescendo\" number=\"1\"/>\n          </direction-type>\n        </direction>\n      <note>\n        <unpitched>\n          <display-step>A</display-step>\n          <display-octave>5</display-octave>\n          </unpitched>\n        <duration>24</duration>\n        <instrument id=\"P1-I50\"/>\n        <voice>1</voice>\n        <type>quarter</type>\n        <stem>up</stem>\n        <notehead>x</notehead>\n        <notations>\n          <ornaments>\n            <tremolo type=\"single\">3</tremolo>\n            </ornaments>\n          </notations>\n        </note>\n      <direction placement=\"below\">\n        <direction-type>\n          <wedge type=\"stop\" number=\"1\"/>\n          </direction-type>\n        </direction>\n      </measure>\n    <measure number=\"4\">\n      <note>\n        <unpitched>\n          <display-step>A</display-step>\n          <display-octave>4</display-octave>\n          </unpitched>\n        <duration>18</duration>\n        <instrument id=\"P1-I42\"/>\n        <voice>1</voice>\n        <type>eighth</type>\n        <dot/>\n        <stem>up</stem>\n        <beam number=\"1\">begin</beam>\n        </note>\n      <note>\n        <chord/>\n        <unpitched>\n          <display-step>D</display-step>\n          <display-octave>5</display-octave>\n          </unpitched>\n        <duration>18</duration>\n        <instrument id=\"P1-I48\"/>\n        <voice>1</voice>\n        <type>eighth</type>\n        <dot/>\n        <stem>up</stem>\n        </note>\n      <note>\n        <unpitched>\n          <display-step>A</display-step>\n          <display-octave>4</display-octave>\n          </unpitched>\n        <duration>6</duration>\n        <instrument id=\"P1-I42\"/>\n        <voice>1</voice>\n        <type>16th</type>\n        <stem>up</stem>\n        <beam number=\"1\">end</beam>\n        <beam number=\"2\">backward hook</beam>\n        </note>\n      <note>\n        <chord/>\n        <unpitched>\n          <display-step>D</display-step>\n          <display-octave>5</display-octave>\n          </unpitched>\n        <duration>6</duration>\n        <instrument id=\"P1-I48\"/>\n        <voice>1</voice>\n        <type>16th</type>\n        <stem>up</stem>\n        </note>\n      <note>\n        <rest/>\n        <duration>24</duration>\n        <voice>1</voice>\n        <type>quarter</type>\n        </note>\n      <note>\n        <rest/>\n        <duration>48</duration>\n        <voice>1</voice>\n        <type>half</type>\n        </note>\n      </measure>\n    <measure number=\"5\">\n      <attributes>\n        <measure-style>\n          <measure-repeat type=\"start\">1</measure-repeat>\n          </measure-style>\n        </attributes>\n      <note>\n        <unpitched>\n          <display-step>A</display-step>\n          <display-octave>4</display-octave>\n          </unpitched>\n        <duration>18</duration>\n        <instrument id=\"P1-I42\"/>\n        <voice>1</voice>\n        <type>eighth</type>\n        <dot/>\n        <stem>up</stem>\n        <beam number=\"1\">begin</beam>\n        </note>\n      <note>\n        <chord/>\n        <unpitched>\n          <display-step>D</display-step>\n          <display-octave>5</display-octave>\n          </unpitched>\n        <duration>18</duration>\n        <instrument id=\"P1-I48\"/>\n        <voice>1</voice>\n        <type>eighth</type>\n        <dot/>\n        <stem>up</stem>\n        </note>\n      <note>\n        <unpitched>\n          <display-step>A</display-step>\n          <display-octave>4</display-octave>\n          </unpitched>\n        <duration>6</duration>\n        <instrument id=\"P1-I42\"/>\n        <voice>1</voice>\n        <type>16th</type>\n        <stem>up</stem>\n        <beam number=\"1\">end</beam>\n        <beam number=\"2\">backward hook</beam>\n        </note>\n      <note>\n        <chord/>\n        <unpitched>\n          <display-step>D</display-step>\n          <display-octave>5</display-octave>\n          </unpitched>\n        <duration>6</duration>\n        <instrument id=\"P1-I48\"/>\n        <voice>1</voice>\n        <type>16th</type>\n        <stem>up</stem>\n        </note>\n      <note>\n        <rest/>\n        <duration>24</duration>\n        <voice>1</voice>\n        <type>quarter</type>\n        </note>\n      <note>\n        <rest/>\n        <duration>48</duration>\n        <voice>1</voice>\n        <type>half</type>\n        </note>\n      </measure>\n    <measure number=\"6\">\n      <attributes>\n        <measure-style>\n          <measure-repeat type=\"stop\"></measure-repeat>\n          </measure-style>\n        </attributes>\n      <note>\n        <rest measure=\"yes\"/>\n        <duration>96</duration>\n        <voice>1</voice>\n        </note>\n      </measure>\n    <measure number=\"7\">\n      <note>\n        <rest measure=\"yes\"/>\n        <duration>96</duration>\n        <voice>1</voice>\n        </note>\n      </measure>\n    <measure number=\"8\">\n      <note>\n        <rest measure=\"yes\"/>\n        <duration>96</duration>\n        <voice>1</voice>\n        </note>\n      </measure>\n    <measure number=\"9\">\n      <note>\n        <unpitched>\n          <display-step>A</display-step>\n          <display-octave>4</display-octave>\n          </unpitched>\n        <duration>18</duration>\n        <instrument id=\"P1-I42\"/>\n        <voice>1</voice>\n        <type>eighth</type>\n        <dot/>\n        <stem>up</stem>\n        <beam number=\"1\">begin</beam>\n        </note>\n      <note>\n        <chord/>\n        <unpitched>\n          <display-step>D</display-step>\n          <display-octave>5</display-octave>\n          </unpitched>\n        <duration>18</duration>\n        <instrument id=\"P1-I48\"/>\n        <voice>1</voice>\n        <type>eighth</type>\n        <dot/>\n        <stem>up</stem>\n        </note>\n      <note>\n        <unpitched>\n          <display-step>A</display-step>\n          <display-octave>4</display-octave>\n          </unpitched>\n        <duration>6</duration>\n        <instrument id=\"P1-I42\"/>\n        <voice>1</voice>\n        <type>16th</type>\n        <stem>up</stem>\n        <beam number=\"1\">end</beam>\n        <beam number=\"2\">backward hook</beam>\n        </note>\n      <note>\n        <chord/>\n        <unpitched>\n          <display-step>D</display-step>\n          <display-octave>5</display-octave>\n          </unpitched>\n        <duration>6</duration>\n        <instrument id=\"P1-I48\"/>\n        <voice>1</voice>\n        <type>16th</type>\n        <stem>up</stem>\n        </note>\n      <note>\n        <rest/>\n        <duration>24</duration>\n        <voice>1</voice>\n        <type>quarter</type>\n        </note>\n      <note>\n        <rest/>\n        <duration>48</duration>\n        <voice>1</voice>\n        <type>half</type>\n        </note>\n      </measure>\n    <measure number=\"10\">\n      <note>\n        <rest measure=\"yes\"/>\n        <duration>96</duration>\n        <voice>1</voice>\n        </note>\n      </measure>\n    <measure number=\"11\">\n      <note>\n        <unpitched>\n          <display-step>A</display-step>\n          <display-octave>4</display-octave>\n          </unpitched>\n        <duration>18</duration>\n        <instrument id=\"P1-I42\"/>\n        <voice>1</voice>\n        <type>eighth</type>\n        <dot/>\n        <stem>up</stem>\n        <beam number=\"1\">begin</beam>\n        </note>\n      <note>\n        <chord/>\n        <unpitched>\n          <display-step>D</display-step>\n          <display-octave>5</display-octave>\n          </unpitched>\n        <duration>18</duration>\n        <instrument id=\"P1-I48\"/>\n        <voice>1</voice>\n        <type>eighth</type>\n        <dot/>\n        <stem>up</stem>\n        </note>\n      <note>\n        <unpitched>\n          <display-step>A</display-step>\n          <display-octave>4</display-octave>\n          </unpitched>\n        <duration>6</duration>\n        <instrument id=\"P1-I42\"/>\n        <voice>1</voice>\n        <type>16th</type>\n        <stem>up</stem>\n        <beam number=\"1\">end</beam>\n        <beam number=\"2\">backward hook</beam>\n        </note>\n      <note>\n        <chord/>\n        <unpitched>\n          <display-step>D</display-step>\n          <display-octave>5</display-octave>\n          </unpitched>\n        <duration>6</duration>\n        <instrument id=\"P1-I48\"/>\n        <voice>1</voice>\n        <type>16th</type>\n        <stem>up</stem>\n        </note>\n      <note>\n        <rest/>\n        <duration>24</duration>\n        <voice>1</voice>\n        <type>quarter</type>\n        </note>\n      <note>\n        <rest/>\n        <duration>18</duration>\n        <voice>1</voice>\n        <type>eighth</type>\n        <dot/>\n        </note>\n      <note>\n        <unpitched>\n          <display-step>A</display-step>\n          <display-octave>4</display-octave>\n          </unpitched>\n        <duration>6</duration>\n        <instrument id=\"P1-I42\"/>\n        <voice>1</voice>\n        <type>16th</type>\n        <stem>up</stem>\n        </note>\n      <note>\n        <unpitched>\n          <display-step>C</display-step>\n          <display-octave>5</display-octave>\n          </unpitched>\n        <duration>12</duration>\n        <instrument id=\"P1-I39\"/>\n        <voice>1</voice>\n        <type>eighth</type>\n        <stem>up</stem>\n        <beam number=\"1\">begin</beam>\n        <notations>\n          <articulations>\n            <accent placement=\"above\"/>\n            </articulations>\n          </notations>\n        </note>\n      <note>\n        <unpitched>\n          <display-step>A</display-step>\n          <display-octave>4</display-octave>\n          </unpitched>\n        <duration>6</duration>\n        <instrument id=\"P1-I42\"/>\n        <voice>1</voice>\n        <type>16th</type>\n        <stem>up</stem>\n        <beam number=\"1\">continue</beam>\n        <beam number=\"2\">begin</beam>\n        </note>\n      <note>\n        <unpitched>\n          <display-step>A</display-step>\n          <display-octave>4</display-octave>\n          </unpitched>\n        <duration>6</duration>\n        <instrument id=\"P1-I42\"/>\n        <voice>1</voice>\n        <type>16th</type>\n        <stem>up</stem>\n        <beam number=\"1\">end</beam>\n        <beam number=\"2\">end</beam>\n        </note>\n      </measure>\n    <measure number=\"12\">\n      <note>\n        <rest measure=\"yes\"/>\n        <duration>96</duration>\n        <voice>1</voice>\n        </note>\n      </measure>\n    <measure number=\"13\">\n      <note>\n        <unpitched>\n          <display-step>F</display-step>\n          <display-octave>4</display-octave>\n          </unpitched>\n        <duration>18</duration>\n        <instrument id=\"P1-I37\"/>\n        <voice>1</voice>\n        <type>eighth</type>\n        <dot/>\n        <stem>up</stem>\n        <beam number=\"1\">begin</beam>\n        </note>\n      <note>\n        <chord/>\n        <unpitched>\n          <display-step>A</display-step>\n          <display-octave>4</display-octave>\n          </unpitched>\n        <duration>18</duration>\n        <instrument id=\"P1-I42\"/>\n        <voice>1</voice>\n        <type>eighth</type>\n        <dot/>\n        <stem>up</stem>\n        </note>\n      <note>\n        <chord/>\n        <unpitched>\n          <display-step>D</display-step>\n          <display-octave>5</display-octave>\n          </unpitched>\n        <duration>18</duration>\n        <instrument id=\"P1-I48\"/>\n        <voice>1</voice>\n        <type>eighth</type>\n        <dot/>\n        <stem>up</stem>\n        </note>\n      <note>\n        <unpitched>\n          <display-step>A</display-step>\n          <display-octave>4</display-octave>\n          </unpitched>\n        <duration>6</duration>\n        <instrument id=\"P1-I42\"/>\n        <voice>1</voice>\n        <type>16th</type>\n        <stem>up</stem>\n        <beam number=\"1\">end</beam>\n        <beam number=\"2\">backward hook</beam>\n        </note>\n      <note>\n        <chord/>\n        <unpitched>\n          <display-step>D</display-step>\n          <display-octave>5</display-octave>\n          </unpitched>\n        <duration>6</duration>\n        <instrument id=\"P1-I48\"/>\n        <voice>1</voice>\n        <type>16th</type>\n        <stem>up</stem>\n        </note>\n      <note>\n        <unpitched>\n          <display-step>F</display-step>\n          <display-octave>4</display-octave>\n          </unpitched>\n        <duration>24</duration>\n        <instrument id=\"P1-I37\"/>\n        <voice>1</voice>\n        <type>quarter</type>\n        <stem>up</stem>\n        </note>\n      <note>\n        <unpitched>\n          <display-step>F</display-step>\n          <display-octave>4</display-octave>\n          </unpitched>\n        <duration>18</duration>\n        <instrument id=\"P1-I37\"/>\n        <voice>1</voice>\n        <type>eighth</type>\n        <dot/>\n        <stem>up</stem>\n        <beam number=\"1\">begin</beam>\n        </note>\n      <note>\n        <unpitched>\n          <display-step>D</display-step>\n          <display-octave>5</display-octave>\n          </unpitched>\n        <duration>6</duration>\n        <instrument id=\"P1-I48\"/>\n        <voice>1</voice>\n        <type>16th</type>\n        <stem>up</stem>\n        <beam number=\"1\">end</beam>\n        <beam number=\"2\">backward hook</beam>\n        </note>\n      <note>\n        <unpitched>\n          <display-step>F</display-step>\n          <display-octave>4</display-octave>\n          </unpitched>\n        <duration>12</duration>\n        <instrument id=\"P1-I37\"/>\n        <voice>1</voice>\n        <type>eighth</type>\n        <stem>up</stem>\n        <beam number=\"1\">begin</beam>\n        </note>\n      <note>\n        <chord/>\n        <unpitched>\n          <display-step>A</display-step>\n          <display-octave>4</display-octave>\n          </unpitched>\n        <duration>12</duration>\n        <instrument id=\"P1-I42\"/>\n        <voice>1</voice>\n        <type>eighth</type>\n        <stem>up</stem>\n        </note>\n      <note>\n        <unpitched>\n          <display-step>A</display-step>\n          <display-octave>4</display-octave>\n          </unpitched>\n        <duration>6</duration>\n        <instrument id=\"P1-I42\"/>\n        <voice>1</voice>\n        <type>16th</type>\n        <stem>up</stem>\n        <beam number=\"1\">continue</beam>\n        <beam number=\"2\">begin</beam>\n        </note>\n      <note>\n        <unpitched>\n          <display-step>A</display-step>\n          <display-octave>4</display-octave>\n          </unpitched>\n        <duration>6</duration>\n        <instrument id=\"P1-I42\"/>\n        <voice>1</voice>\n        <type>16th</type>\n        <stem>up</stem>\n        <beam number=\"1\">end</beam>\n        <beam number=\"2\">end</beam>\n        </note>\n      </measure>\n    <measure number=\"14\">\n      <note>\n        <unpitched>\n          <display-step>F</display-step>\n          <display-octave>4</display-octave>\n          </unpitched>\n        <duration>18</duration>\n        <instrument id=\"P1-I37\"/>\n        <voice>1</voice>\n        <type>eighth</type>\n        <dot/>\n        <stem>up</stem>\n        <beam number=\"1\">begin</beam>\n        </note>\n      <note>\n        <chord/>\n        <unpitched>\n          <display-step>A</display-step>\n          <display-octave>4</display-octave>\n          </unpitched>\n        <duration>18</duration>\n        <instrument id=\"P1-I42\"/>\n        <voice>1</voice>\n        <type>eighth</type>\n        <dot/>\n        <stem>up</stem>\n        </note>\n      <note>\n        <chord/>\n        <unpitched>\n          <display-step>D</display-step>\n          <display-octave>5</display-octave>\n          </unpitched>\n        <duration>18</duration>\n        <instrument id=\"P1-I48\"/>\n        <voice>1</voice>\n        <type>eighth</type>\n        <dot/>\n        <stem>up</stem>\n        </note>\n      <note>\n        <unpitched>\n          <display-step>A</display-step>\n          <display-octave>4</display-octave>\n          </unpitched>\n        <duration>6</duration>\n        <instrument id=\"P1-I42\"/>\n        <voice>1</voice>\n        <type>16th</type>\n        <stem>up</stem>\n        <beam number=\"1\">end</beam>\n        <beam number=\"2\">backward hook</beam>\n        </note>\n      <note>\n        <chord/>\n        <unpitched>\n          <display-step>D</display-step>\n          <display-octave>5</display-octave>\n          </unpitched>\n        <duration>6</duration>\n        <instrument id=\"P1-I48\"/>\n        <voice>1</voice>\n        <type>16th</type>\n        <stem>up</stem>\n        </note>\n      <note>\n        <unpitched>\n          <display-step>F</display-step>\n          <display-octave>4</display-octave>\n          </unpitched>\n        <duration>24</duration>\n        <instrument id=\"P1-I37\"/>\n        <voice>1</voice>\n        <type>quarter</type>\n        <stem>up</stem>\n        </note>\n      <note>\n        <unpitched>\n          <display-step>F</display-step>\n          <display-octave>4</display-octave>\n          </unpitched>\n        <duration>6</duration>\n        <instrument id=\"P1-I37\"/>\n        <voice>1</voice>\n        <type>16th</type>\n        <stem>up</stem>\n        <beam number=\"1\">begin</beam>\n        <beam number=\"2\">forward hook</beam>\n        </note>\n      <note>\n        <unpitched>\n          <display-step>D</display-step>\n          <display-octave>5</display-octave>\n          </unpitched>\n        <duration>12</duration>\n        <instrument id=\"P1-I48\"/>\n        <voice>1</voice>\n        <type>eighth</type>\n        <stem>up</stem>\n        <beam number=\"1\">continue</beam>\n        </note>\n      <note>\n        <unpitched>\n          <display-step>D</display-step>\n          <display-octave>5</display-octave>\n          </unpitched>\n        <duration>6</duration>\n        <instrument id=\"P1-I48\"/>\n        <voice>1</voice>\n        <type>16th</type>\n        <stem>up</stem>\n        <beam number=\"1\">end</beam>\n        <beam number=\"2\">backward hook</beam>\n        </note>\n      <note>\n        <unpitched>\n          <display-step>F</display-step>\n          <display-octave>4</display-octave>\n          </unpitched>\n        <duration>12</duration>\n        <instrument id=\"P1-I37\"/>\n        <voice>1</voice>\n        <type>eighth</type>\n        <stem>up</stem>\n        <beam number=\"1\">begin</beam>\n        </note>\n      <note>\n        <chord/>\n        <unpitched>\n          <display-step>A</display-step>\n          <display-octave>4</display-octave>\n          </unpitched>\n        <duration>12</duration>\n        <instrument id=\"P1-I42\"/>\n        <voice>1</voice>\n        <type>eighth</type>\n        <stem>up</stem>\n        </note>\n      <note>\n        <unpitched>\n          <display-step>A</display-step>\n          <display-octave>4</display-octave>\n          </unpitched>\n        <duration>6</duration>\n        <instrument id=\"P1-I42\"/>\n        <voice>1</voice>\n        <type>16th</type>\n        <stem>up</stem>\n        <beam number=\"1\">continue</beam>\n        <beam number=\"2\">begin</beam>\n        </note>\n      <note>\n        <unpitched>\n          <display-step>A</display-step>\n          <display-octave>4</display-octave>\n          </unpitched>\n        <duration>6</duration>\n        <instrument id=\"P1-I42\"/>\n        <voice>1</voice>\n        <type>16th</type>\n        <stem>up</stem>\n        <beam number=\"1\">end</beam>\n        <beam number=\"2\">end</beam>\n        </note>\n      </measure>\n    <measure number=\"15\">\n      <note>\n        <rest measure=\"yes\"/>\n        <duration>96</duration>\n        <voice>1</voice>\n        </note>\n      </measure>\n    <measure number=\"16\">\n      <note>\n        <rest measure=\"yes\"/>\n        <duration>96</duration>\n        <voice>1</voice>\n        </note>\n      </measure>\n    <measure number=\"17\">\n      <note>\n        <unpitched>\n          <display-step>F</display-step>\n          <display-octave>4</display-octave>\n          </unpitched>\n        <duration>18</duration>\n        <instrument id=\"P1-I37\"/>\n        <voice>1</voice>\n        <type>eighth</type>\n        <dot/>\n        <stem>up</stem>\n        <beam number=\"1\">begin</beam>\n        </note>\n      <note>\n        <chord/>\n        <unpitched>\n          <display-step>A</display-step>\n          <display-octave>4</display-octave>\n          </unpitched>\n        <duration>18</duration>\n        <instrument id=\"P1-I42\"/>\n        <voice>1</voice>\n        <type>eighth</type>\n        <dot/>\n        <stem>up</stem>\n        </note>\n      <note>\n        <unpitched>\n          <display-step>E</display-step>\n          <display-octave>5</display-octave>\n          </unpitched>\n        <duration>6</duration>\n        <instrument id=\"P1-I51\"/>\n        <voice>1</voice>\n        <type>16th</type>\n        <stem>up</stem>\n        <beam number=\"1\">end</beam>\n        <beam number=\"2\">backward hook</beam>\n        </note>\n      <note>\n        <unpitched>\n          <display-step>F</display-step>\n          <display-octave>4</display-octave>\n          </unpitched>\n        <duration>12</duration>\n        <instrument id=\"P1-I37\"/>\n        <voice>1</voice>\n        <type>eighth</type>\n        <stem>up</stem>\n        <beam number=\"1\">begin</beam>\n        </note>\n      <note>\n        <chord/>\n        <unpitched>\n          <display-step>A</display-step>\n          <display-octave>4</display-octave>\n          </unpitched>\n        <duration>12</duration>\n        <instrument id=\"P1-I42\"/>\n        <voice>1</voice>\n        <type>eighth</type>\n        <stem>up</stem>\n        </note>\n      <note>\n        <unpitched>\n          <display-step>D</display-step>\n          <display-octave>5</display-octave>\n          </unpitched>\n        <duration>12</duration>\n        <instrument id=\"P1-I48\"/>\n        <voice>1</voice>\n        <type>eighth</type>\n        <stem>up</stem>\n        <beam number=\"1\">end</beam>\n        </note>\n      <note>\n        <unpitched>\n          <display-step>F</display-step>\n          <display-octave>4</display-octave>\n          </unpitched>\n        <duration>6</duration>\n        <instrument id=\"P1-I37\"/>\n        <voice>1</voice>\n        <type>16th</type>\n        <stem>up</stem>\n        <beam number=\"1\">begin</beam>\n        <beam number=\"2\">forward hook</beam>\n        </note>\n      <note>\n        <chord/>\n        <unpitched>\n          <display-step>A</display-step>\n          <display-octave>4</display-octave>\n          </unpitched>\n        <duration>6</duration>\n        <instrument id=\"P1-I42\"/>\n        <voice>1</voice>\n        <type>16th</type>\n        <stem>up</stem>\n        </note>\n      <note>\n        <unpitched>\n          <display-step>A</display-step>\n          <display-octave>4</display-octave>\n          </unpitched>\n        <duration>18</duration>\n        <instrument id=\"P1-I42\"/>\n        <voice>1</voice>\n        <type>eighth</type>\n        <dot/>\n        <stem>up</stem>\n        <beam number=\"1\">end</beam>\n        </note>\n      <note>\n        <unpitched>\n          <display-step>F</display-step>\n          <display-octave>4</display-octave>\n          </unpitched>\n        <duration>18</duration>\n        <instrument id=\"P1-I37\"/>\n        <voice>1</voice>\n        <type>eighth</type>\n        <dot/>\n        <stem>up</stem>\n        <beam number=\"1\">begin</beam>\n        <notations>\n          <articulations>\n            <accent placement=\"above\"/>\n            </articulations>\n          </notations>\n        </note>\n      <note>\n        <chord/>\n        <unpitched>\n          <display-step>A</display-step>\n          <display-octave>4</display-octave>\n          </unpitched>\n        <duration>18</duration>\n        <instrument id=\"P1-I42\"/>\n        <voice>1</voice>\n        <type>eighth</type>\n        <dot/>\n        <stem>up</stem>\n        </note>\n      <note>\n        <chord/>\n        <unpitched>\n          <display-step>C</display-step>\n          <display-octave>5</display-octave>\n          </unpitched>\n        <duration>18</duration>\n        <instrument id=\"P1-I39\"/>\n        <voice>1</voice>\n        <type>eighth</type>\n        <dot/>\n        <stem>up</stem>\n        </note>\n      <note>\n        <unpitched>\n          <display-step>A</display-step>\n          <display-octave>4</display-octave>\n          </unpitched>\n        <duration>6</duration>\n        <instrument id=\"P1-I42\"/>\n        <voice>1</voice>\n        <type>16th</type>\n        <stem>up</stem>\n        <beam number=\"1\">end</beam>\n        <beam number=\"2\">backward hook</beam>\n        </note>\n      </measure>\n    <measure number=\"18\">\n      <note>\n        <rest measure=\"yes\"/>\n        <duration>96</duration>\n        <voice>1</voice>\n        </note>\n      </measure>\n    <measure number=\"19\">\n      <note>\n        <rest measure=\"yes\"/>\n        <duration>96</duration>\n        <voice>1</voice>\n        </note>\n      </measure>\n    <measure number=\"20\">\n      <note>\n        <unpitched>\n          <display-step>F</display-step>\n          <display-octave>4</display-octave>\n          </unpitched>\n        <duration>6</duration>\n        <instrument id=\"P1-I37\"/>\n        <voice>1</voice>\n        <type>16th</type>\n        <stem>up</stem>\n        <beam number=\"1\">begin</beam>\n        <beam number=\"2\">begin</beam>\n        </note>\n      <note>\n        <chord/>\n        <unpitched>\n          <display-step>F</display-step>\n          <display-octave>5</display-octave>\n          </unpitched>\n        <duration>6</duration>\n        <instrument id=\"P1-I52\"/>\n        <voice>1</voice>\n        <type>16th</type>\n        <stem>up</stem>\n        <notehead>x</notehead>\n        </note>\n      <note>\n        <unpitched>\n          <display-step>C</display-step>\n          <display-octave>5</display-octave>\n          </unpitched>\n        <duration>6</duration>\n        <instrument id=\"P1-I1\"/>\n        <voice>1</voice>\n        <type>16th</type>\n        <stem>up</stem>\n        <notehead>diamond</notehead>\n        <beam number=\"1\">continue</beam>\n        <beam number=\"2\">continue</beam>\n        </note>\n      <note>\n        <unpitched>\n          <display-step>F</display-step>\n          <display-octave>5</display-octave>\n          </unpitched>\n        <duration>6</duration>\n        <instrument id=\"P1-I52\"/>\n        <voice>1</voice>\n        <type>16th</type>\n        <stem>up</stem>\n        <notehead>x</notehead>\n        <beam number=\"1\">continue</beam>\n        <beam number=\"2\">continue</beam>\n        </note>\n      <note>\n        <unpitched>\n          <display-step>F</display-step>\n          <display-octave>4</display-octave>\n          </unpitched>\n        <duration>6</duration>\n        <instrument id=\"P1-I37\"/>\n        <voice>1</voice>\n        <type>16th</type>\n        <stem>up</stem>\n        <beam number=\"1\">end</beam>\n        <beam number=\"2\">end</beam>\n        </note>\n      <note>\n        <unpitched>\n          <display-step>C</display-step>\n          <display-octave>5</display-octave>\n          </unpitched>\n        <duration>12</duration>\n        <instrument id=\"P1-I39\"/>\n        <voice>1</voice>\n        <type>eighth</type>\n        <stem>up</stem>\n        <beam number=\"1\">begin</beam>\n        <notations>\n          <articulations>\n            <accent placement=\"above\"/>\n            </articulations>\n          </notations>\n        </note>\n      <note>\n        <chord/>\n        <unpitched>\n          <display-step>F</display-step>\n          <display-octave>5</display-octave>\n          </unpitched>\n        <duration>12</duration>\n        <instrument id=\"P1-I52\"/>\n        <voice>1</voice>\n        <type>eighth</type>\n        <stem>up</stem>\n        <notehead>x</notehead>\n        </note>\n      <note>\n        <unpitched>\n          <display-step>F</display-step>\n          <display-octave>5</display-octave>\n          </unpitched>\n        <duration>6</duration>\n        <instrument id=\"P1-I52\"/>\n        <voice>1</voice>\n        <type>16th</type>\n        <stem>up</stem>\n        <notehead>x</notehead>\n        <beam number=\"1\">continue</beam>\n        <beam number=\"2\">begin</beam>\n        </note>\n      <note>\n        <unpitched>\n          <display-step>C</display-step>\n          <display-octave>5</display-octave>\n          </unpitched>\n        <duration>6</duration>\n        <instrument id=\"P1-I1\"/>\n        <voice>1</voice>\n        <type>16th</type>\n        <stem>up</stem>\n        <notehead>diamond</notehead>\n        <beam number=\"1\">end</beam>\n        <beam number=\"2\">end</beam>\n        </note>\n      <note>\n        <unpitched>\n          <display-step>F</display-step>\n          <display-octave>5</display-octave>\n          </unpitched>\n        <duration>6</duration>\n        <instrument id=\"P1-I52\"/>\n        <voice>1</voice>\n        <type>16th</type>\n        <stem>up</stem>\n        <notehead>x</notehead>\n        <beam number=\"1\">begin</beam>\n        <beam number=\"2\">begin</beam>\n        </note>\n      <note>\n        <unpitched>\n          <display-step>F</display-step>\n          <display-octave>4</display-octave>\n          </unpitched>\n        <duration>6</duration>\n        <instrument id=\"P1-I37\"/>\n        <voice>1</voice>\n        <type>16th</type>\n        <stem>up</stem>\n        <beam number=\"1\">continue</beam>\n        <beam number=\"2\">end</beam>\n        </note>\n      <note dynamics=\"71.11\">\n        <chord/>\n        <unpitched>\n          <display-step>C</display-step>\n          <display-octave>5</display-octave>\n          </unpitched>\n        <duration>6</duration>\n        <instrument id=\"P1-I1\"/>\n        <voice>1</voice>\n        <type>16th</type>\n        <stem>up</stem>\n        <notehead>diamond</notehead>\n        </note>\n      <note>\n        <unpitched>\n          <display-step>F</display-step>\n          <display-octave>4</display-octave>\n          </unpitched>\n        <duration>12</duration>\n        <instrument id=\"P1-I37\"/>\n        <voice>1</voice>\n        <type>eighth</type>\n        <stem>up</stem>\n        <beam number=\"1\">end</beam>\n        </note>\n      <note>\n        <chord/>\n        <unpitched>\n          <display-step>F</display-step>\n          <display-octave>5</display-octave>\n          </unpitched>\n        <duration>12</duration>\n        <instrument id=\"P1-I52\"/>\n        <voice>1</voice>\n        <type>eighth</type>\n        <stem>up</stem>\n        <notehead>x</notehead>\n        </note>\n      <note>\n        <unpitched>\n          <display-step>C</display-step>\n          <display-octave>5</display-octave>\n          </unpitched>\n        <duration>12</duration>\n        <instrument id=\"P1-I39\"/>\n        <voice>1</voice>\n        <type>eighth</type>\n        <stem>up</stem>\n        <beam number=\"1\">begin</beam>\n        <notations>\n          <articulations>\n            <accent placement=\"above\"/>\n            </articulations>\n          </notations>\n        </note>\n      <note>\n        <chord/>\n        <unpitched>\n          <display-step>F</display-step>\n          <display-octave>5</display-octave>\n          </unpitched>\n        <duration>12</duration>\n        <instrument id=\"P1-I52\"/>\n        <voice>1</voice>\n        <type>eighth</type>\n        <stem>up</stem>\n        <notehead>x</notehead>\n        </note>\n      <note>\n        <unpitched>\n          <display-step>F</display-step>\n          <display-octave>5</display-octave>\n          </unpitched>\n        <duration>6</duration>\n        <instrument id=\"P1-I52\"/>\n        <voice>1</voice>\n        <type>16th</type>\n        <stem>up</stem>\n        <notehead>x</notehead>\n        <beam number=\"1\">continue</beam>\n        <beam number=\"2\">begin</beam>\n        </note>\n      <note>\n        <unpitched>\n          <display-step>C</display-step>\n          <display-octave>5</display-octave>\n          </unpitched>\n        <duration>3</duration>\n        <instrument id=\"P1-I1\"/>\n        <voice>1</voice>\n        <type>32nd</type>\n        <stem>up</stem>\n        <notehead>diamond</notehead>\n        <beam number=\"1\">continue</beam>\n        <beam number=\"2\">continue</beam>\n        <beam number=\"3\">begin</beam>\n        </note>\n      <note>\n        <unpitched>\n          <display-step>C</display-step>\n          <display-octave>5</display-octave>\n          </unpitched>\n        <duration>3</duration>\n        <instrument id=\"P1-I1\"/>\n        <voice>1</voice>\n        <type>32nd</type>\n        <stem>up</stem>\n        <notehead>diamond</notehead>\n        <beam number=\"1\">end</beam>\n        <beam number=\"2\">end</beam>\n        <beam number=\"3\">end</beam>\n        </note>\n      </measure>\n    <measure number=\"21\">\n      <note>\n        <rest measure=\"yes\"/>\n        <duration>96</duration>\n        <voice>1</voice>\n        </note>\n      </measure>\n    <measure number=\"22\">\n      <note>\n        <rest measure=\"yes\"/>\n        <duration>96</duration>\n        <voice>1</voice>\n        </note>\n      </measure>\n    <measure number=\"23\">\n      <direction placement=\"below\">\n        <direction-type>\n          <wedge type=\"crescendo\" number=\"1\"/>\n          </direction-type>\n        </direction>\n      <note>\n        <unpitched>\n          <display-step>F</display-step>\n          <display-octave>4</display-octave>\n          </unpitched>\n        <duration>12</duration>\n        <instrument id=\"P1-I37\"/>\n        <voice>1</voice>\n        <type>eighth</type>\n        <stem>up</stem>\n        <beam number=\"1\">begin</beam>\n        </note>\n      <note>\n        <chord/>\n        <unpitched>\n          <display-step>A</display-step>\n          <display-octave>4</display-octave>\n          </unpitched>\n        <duration>12</duration>\n        <instrument id=\"P1-I42\"/>\n        <voice>1</voice>\n        <type>eighth</type>\n        <stem>up</stem>\n        </note>\n      <note>\n        <chord/>\n        <unpitched>\n          <display-step>F</display-step>\n          <display-octave>5</display-octave>\n          </unpitched>\n        <duration>12</duration>\n        <instrument id=\"P1-I52\"/>\n        <voice>1</voice>\n        <type>eighth</type>\n        <stem>up</stem>\n        <notehead>x</notehead>\n        </note>\n      <note>\n        <unpitched>\n          <display-step>F</display-step>\n          <display-octave>4</display-octave>\n          </unpitched>\n        <duration>12</duration>\n        <instrument id=\"P1-I37\"/>\n        <voice>1</voice>\n        <type>eighth</type>\n        <stem>up</stem>\n        <beam number=\"1\">end</beam>\n        </note>\n      <note>\n        <chord/>\n        <unpitched>\n          <display-step>A</display-step>\n          <display-octave>4</display-octave>\n          </unpitched>\n        <duration>12</duration>\n        <instrument id=\"P1-I42\"/>\n        <voice>1</voice>\n        <type>eighth</type>\n        <stem>up</stem>\n        </note>\n      <note>\n        <chord/>\n        <unpitched>\n          <display-step>F</display-step>\n          <display-octave>5</display-octave>\n          </unpitched>\n        <duration>12</duration>\n        <instrument id=\"P1-I52\"/>\n        <voice>1</voice>\n        <type>eighth</type>\n        <stem>up</stem>\n        <notehead>x</notehead>\n        </note>\n      <note>\n        <unpitched>\n          <display-step>F</display-step>\n          <display-octave>4</display-octave>\n          </unpitched>\n        <duration>12</duration>\n        <instrument id=\"P1-I37\"/>\n        <voice>1</voice>\n        <type>eighth</type>\n        <stem>up</stem>\n        <beam number=\"1\">begin</beam>\n        </note>\n      <note>\n        <chord/>\n        <unpitched>\n          <display-step>A</display-step>\n          <display-octave>4</display-octave>\n          </unpitched>\n        <duration>12</duration>\n        <instrument id=\"P1-I42\"/>\n        <voice>1</voice>\n        <type>eighth</type>\n        <stem>up</stem>\n        </note>\n      <note>\n        <chord/>\n        <unpitched>\n          <display-step>F</display-step>\n          <display-octave>5</display-octave>\n          </unpitched>\n        <duration>12</duration>\n        <instrument id=\"P1-I52\"/>\n        <voice>1</voice>\n        <type>eighth</type>\n        <stem>up</stem>\n        <notehead>x</notehead>\n        </note>\n      <note>\n        <unpitched>\n          <display-step>F</display-step>\n          <display-octave>4</display-octave>\n          </unpitched>\n        <duration>12</duration>\n        <instrument id=\"P1-I37\"/>\n        <voice>1</voice>\n        <type>eighth</type>\n        <stem>up</stem>\n        <beam number=\"1\">end</beam>\n        </note>\n      <note>\n        <chord/>\n        <unpitched>\n          <display-step>A</display-step>\n          <display-octave>4</display-octave>\n          </unpitched>\n        <duration>12</duration>\n        <instrument id=\"P1-I42\"/>\n        <voice>1</voice>\n        <type>eighth</type>\n        <stem>up</stem>\n        </note>\n      <note>\n        <chord/>\n        <unpitched>\n          <display-step>F</display-step>\n          <display-octave>5</display-octave>\n          </unpitched>\n        <duration>12</duration>\n        <instrument id=\"P1-I52\"/>\n        <voice>1</voice>\n        <type>eighth</type>\n        <stem>up</stem>\n        <notehead>x</notehead>\n        </note>\n      <direction placement=\"below\">\n        <direction-type>\n          <wedge type=\"stop\" number=\"1\"/>\n          </direction-type>\n        </direction>\n      <note>\n        <unpitched>\n          <display-step>C</display-step>\n          <display-octave>5</display-octave>\n          </unpitched>\n        <duration>6</duration>\n        <instrument id=\"P1-I39\"/>\n        <voice>1</voice>\n        <type>16th</type>\n        <stem>up</stem>\n        <beam number=\"1\">begin</beam>\n        <beam number=\"2\">begin</beam>\n        <notations>\n          <articulations>\n            <accent placement=\"above\"/>\n            </articulations>\n          </notations>\n        </note>\n      <note>\n        <chord/>\n        <unpitched>\n          <display-step>F</display-step>\n          <display-octave>5</display-octave>\n          </unpitched>\n        <duration>6</duration>\n        <instrument id=\"P1-I52\"/>\n        <voice>1</voice>\n        <type>16th</type>\n        <stem>up</stem>\n        <notehead>x</notehead>\n        </note>\n      <note>\n        <unpitched>\n          <display-step>F</display-step>\n          <display-octave>4</display-octave>\n          </unpitched>\n        <duration>6</duration>\n        <instrument id=\"P1-I37\"/>\n        <voice>1</voice>\n        <type>16th</type>\n        <stem>up</stem>\n        <beam number=\"1\">continue</beam>\n        <beam number=\"2\">continue</beam>\n        </note>\n      <note>\n        <unpitched>\n          <display-step>F</display-step>\n          <display-octave>4</display-octave>\n          </unpitched>\n        <duration>6</duration>\n        <instrument id=\"P1-I37\"/>\n        <voice>1</voice>\n        <type>16th</type>\n        <stem>up</stem>\n        <beam number=\"1\">continue</beam>\n        <beam number=\"2\">continue</beam>\n        </note>\n      <note>\n        <chord/>\n        <unpitched>\n          <display-step>F</display-step>\n          <display-octave>5</display-octave>\n          </unpitched>\n        <duration>6</duration>\n        <instrument id=\"P1-I52\"/>\n        <voice>1</voice>\n        <type>16th</type>\n        <stem>up</stem>\n        <notehead>x</notehead>\n        </note>\n      <note>\n        <unpitched>\n          <display-step>C</display-step>\n          <display-octave>5</display-octave>\n          </unpitched>\n        <duration>6</duration>\n        <instrument id=\"P1-I39\"/>\n        <voice>1</voice>\n        <type>16th</type>\n        <stem>up</stem>\n        <beam number=\"1\">end</beam>\n        <beam number=\"2\">end</beam>\n        <notations>\n          <articulations>\n            <accent placement=\"above\"/>\n            </articulations>\n          </notations>\n        </note>\n      <note>\n        <unpitched>\n          <display-step>F</display-step>\n          <display-octave>4</display-octave>\n          </unpitched>\n        <duration>6</duration>\n        <instrument id=\"P1-I37\"/>\n        <voice>1</voice>\n        <type>16th</type>\n        <stem>up</stem>\n        <beam number=\"1\">begin</beam>\n        <beam number=\"2\">begin</beam>\n        </note>\n      <note>\n        <chord/>\n        <unpitched>\n          <display-step>F</display-step>\n          <display-octave>5</display-octave>\n          </unpitched>\n        <duration>6</duration>\n        <instrument id=\"P1-I52\"/>\n        <voice>1</voice>\n        <type>16th</type>\n        <stem>up</stem>\n        <notehead>x</notehead>\n        </note>\n      <note>\n        <unpitched>\n          <display-step>F</display-step>\n          <display-octave>4</display-octave>\n          </unpitched>\n        <duration>6</duration>\n        <instrument id=\"P1-I37\"/>\n        <voice>1</voice>\n        <type>16th</type>\n        <stem>up</stem>\n        <beam number=\"1\">continue</beam>\n        <beam number=\"2\">continue</beam>\n        </note>\n      <note>\n        <unpitched>\n          <display-step>C</display-step>\n          <display-octave>5</display-octave>\n          </unpitched>\n        <duration>6</duration>\n        <instrument id=\"P1-I39\"/>\n        <voice>1</voice>\n        <type>16th</type>\n        <stem>up</stem>\n        <beam number=\"1\">continue</beam>\n        <beam number=\"2\">continue</beam>\n        <notations>\n          <articulations>\n            <accent placement=\"above\"/>\n            </articulations>\n          </notations>\n        </note>\n      <note>\n        <chord/>\n        <unpitched>\n          <display-step>F</display-step>\n          <display-octave>5</display-octave>\n          </unpitched>\n        <duration>6</duration>\n        <instrument id=\"P1-I52\"/>\n        <voice>1</voice>\n        <type>16th</type>\n        <stem>up</stem>\n        <notehead>x</notehead>\n        </note>\n      <note>\n        <unpitched>\n          <display-step>F</display-step>\n          <display-octave>4</display-octave>\n          </unpitched>\n        <duration>6</duration>\n        <instrument id=\"P1-I37\"/>\n        <voice>1</voice>\n        <type>16th</type>\n        <stem>up</stem>\n        <beam number=\"1\">end</beam>\n        <beam number=\"2\">end</beam>\n        </note>\n      </measure>\n    <measure number=\"24\">\n      <note>\n        <unpitched>\n          <display-step>F</display-step>\n          <display-octave>4</display-octave>\n          </unpitched>\n        <duration>12</duration>\n        <instrument id=\"P1-I37\"/>\n        <voice>1</voice>\n        <type>eighth</type>\n        <stem>up</stem>\n        <beam number=\"1\">begin</beam>\n        <notations>\n          <articulations>\n            <accent placement=\"above\"/>\n            </articulations>\n          </notations>\n        </note>\n      <note>\n        <chord/>\n        <unpitched>\n          <display-step>A</display-step>\n          <display-octave>5</display-octave>\n          </unpitched>\n        <duration>12</duration>\n        <instrument id=\"P1-I50\"/>\n        <voice>1</voice>\n        <type>eighth</type>\n        <stem>up</stem>\n        <notehead>x</notehead>\n        </note>\n      <note>\n        <unpitched>\n          <display-step>A</display-step>\n          <display-octave>5</display-octave>\n          </unpitched>\n        <duration>6</duration>\n        <instrument id=\"P1-I50\"/>\n        <voice>1</voice>\n        <type>16th</type>\n        <stem>up</stem>\n        <notehead>x</notehead>\n        <beam number=\"1\">continue</beam>\n        <beam number=\"2\">begin</beam>\n        </note>\n      <note>\n        <unpitched>\n          <display-step>C</display-step>\n          <display-octave>5</display-octave>\n          </unpitched>\n        <duration>6</duration>\n        <instrument id=\"P1-I1\"/>\n        <voice>1</voice>\n        <type>16th</type>\n        <stem>up</stem>\n        <notehead>diamond</notehead>\n        <beam number=\"1\">end</beam>\n        <beam number=\"2\">end</beam>\n        </note>\n      <note>\n        <unpitched>\n          <display-step>F</display-step>\n          <display-octave>4</display-octave>\n          </unpitched>\n        <duration>12</duration>\n        <instrument id=\"P1-I37\"/>\n        <voice>1</voice>\n        <type>eighth</type>\n        <stem>up</stem>\n        <beam number=\"1\">begin</beam>\n        <notations>\n          <articulations>\n            <accent placement=\"above\"/>\n            </articulations>\n          </notations>\n        </note>\n      <note>\n        <chord/>\n        <unpitched>\n          <display-step>A</display-step>\n          <display-octave>5</display-octave>\n          </unpitched>\n        <duration>12</duration>\n        <instrument id=\"P1-I50\"/>\n        <voice>1</voice>\n        <type>eighth</type>\n        <stem>up</stem>\n        <notehead>x</notehead>\n        </note>\n      <note dynamics=\"71.11\">\n        <unpitched>\n          <display-step>C</display-step>\n          <display-octave>5</display-octave>\n          </unpitched>\n        <duration>12</duration>\n        <instrument id=\"P1-I1\"/>\n        <voice>1</voice>\n        <type>eighth</type>\n        <stem>up</stem>\n        <notehead>diamond</notehead>\n        <beam number=\"1\">end</beam>\n        </note>\n      <note>\n        <chord/>\n        <unpitched>\n          <display-step>A</display-step>\n          <display-octave>5</display-octave>\n          </unpitched>\n        <duration>12</duration>\n        <instrument id=\"P1-I50\"/>\n        <voice>1</voice>\n        <type>eighth</type>\n        <stem>up</stem>\n        <notehead>x</notehead>\n        </note>\n      <note>\n        <unpitched>\n          <display-step>F</display-step>\n          <display-octave>4</display-octave>\n          </unpitched>\n        <duration>6</duration>\n        <instrument id=\"P1-I37\"/>\n        <voice>1</voice>\n        <type>16th</type>\n        <stem>up</stem>\n        <beam number=\"1\">begin</beam>\n        <beam number=\"2\">begin</beam>\n        <notations>\n          <articulations>\n            <accent placement=\"above\"/>\n            </articulations>\n          </notations>\n        </note>\n      <note>\n        <chord/>\n        <unpitched>\n          <display-step>A</display-step>\n          <display-octave>5</display-octave>\n          </unpitched>\n        <duration>6</duration>\n        <instrument id=\"P1-I50\"/>\n        <voice>1</voice>\n        <type>16th</type>\n        <stem>up</stem>\n        <notehead>x</notehead>\n        </note>\n      <note dynamics=\"71.11\">\n        <unpitched>\n          <display-step>C</display-step>\n          <display-octave>5</display-octave>\n          </unpitched>\n        <duration>6</duration>\n        <instrument id=\"P1-I1\"/>\n        <voice>1</voice>\n        <type>16th</type>\n        <stem>up</stem>\n        <notehead>diamond</notehead>\n        <beam number=\"1\">continue</beam>\n        <beam number=\"2\">continue</beam>\n        </note>\n      <note>\n        <unpitched>\n          <display-step>A</display-step>\n          <display-octave>5</display-octave>\n          </unpitched>\n        <duration>6</duration>\n        <instrument id=\"P1-I50\"/>\n        <voice>1</voice>\n        <type>16th</type>\n        <stem>up</stem>\n        <notehead>x</notehead>\n        <beam number=\"1\">continue</beam>\n        <beam number=\"2\">continue</beam>\n        </note>\n      <note dynamics=\"71.11\">\n        <unpitched>\n          <display-step>C</display-step>\n          <display-octave>5</display-octave>\n          </unpitched>\n        <duration>6</duration>\n        <instrument id=\"P1-I1\"/>\n        <voice>1</voice>\n        <type>16th</type>\n        <stem>up</stem>\n        <notehead>diamond</notehead>\n        <beam number=\"1\">end</beam>\n        <beam number=\"2\">end</beam>\n        </note>\n      <note>\n        <unpitched>\n          <display-step>F</display-step>\n          <display-octave>4</display-octave>\n          </unpitched>\n        <duration>6</duration>\n        <instrument id=\"P1-I37\"/>\n        <voice>1</voice>\n        <type>16th</type>\n        <stem>up</stem>\n        <beam number=\"1\">begin</beam>\n        <beam number=\"2\">begin</beam>\n        <notations>\n          <articulations>\n            <accent placement=\"above\"/>\n            </articulations>\n          </notations>\n        </note>\n      <note>\n        <chord/>\n        <unpitched>\n          <display-step>A</display-step>\n          <display-octave>5</display-octave>\n          </unpitched>\n        <duration>6</duration>\n        <instrument id=\"P1-I50\"/>\n        <voice>1</voice>\n        <type>16th</type>\n        <stem>up</stem>\n        <notehead>x</notehead>\n        </note>\n      <note>\n        <unpitched>\n          <display-step>E</display-step>\n          <display-octave>5</display-octave>\n          </unpitched>\n        <duration>6</duration>\n        <instrument id=\"P1-I51\"/>\n        <voice>1</voice>\n        <type>16th</type>\n        <stem>up</stem>\n        <beam number=\"1\">continue</beam>\n        <beam number=\"2\">continue</beam>\n        </note>\n      <note>\n        <unpitched>\n          <display-step>D</display-step>\n          <display-octave>5</display-octave>\n          </unpitched>\n        <duration>6</duration>\n        <instrument id=\"P1-I48\"/>\n        <voice>1</voice>\n        <type>16th</type>\n        <stem>up</stem>\n        <beam number=\"1\">continue</beam>\n        <beam number=\"2\">continue</beam>\n        </note>\n      <note>\n        <unpitched>\n          <display-step>A</display-step>\n          <display-octave>4</display-octave>\n          </unpitched>\n        <duration>6</duration>\n        <instrument id=\"P1-I42\"/>\n        <voice>1</voice>\n        <type>16th</type>\n        <stem>up</stem>\n        <beam number=\"1\">end</beam>\n        <beam number=\"2\">end</beam>\n        </note>\n      </measure>\n    <measure number=\"25\">\n      <note>\n        <unpitched>\n          <display-step>F</display-step>\n          <display-octave>4</display-octave>\n          </unpitched>\n        <duration>12</duration>\n        <instrument id=\"P1-I37\"/>\n        <voice>1</voice>\n        <type>eighth</type>\n        <stem>up</stem>\n        <beam number=\"1\">begin</beam>\n        <notations>\n          <articulations>\n            <accent placement=\"above\"/>\n            </articulations>\n          </notations>\n        </note>\n      <note>\n        <chord/>\n        <unpitched>\n          <display-step>A</display-step>\n          <display-octave>5</display-octave>\n          </unpitched>\n        <duration>12</duration>\n        <instrument id=\"P1-I50\"/>\n        <voice>1</voice>\n        <type>eighth</type>\n        <stem>up</stem>\n        <notehead>x</notehead>\n        </note>\n      <note>\n        <unpitched>\n          <display-step>A</display-step>\n          <display-octave>5</display-octave>\n          </unpitched>\n        <duration>6</duration>\n        <instrument id=\"P1-I50\"/>\n        <voice>1</voice>\n        <type>16th</type>\n        <stem>up</stem>\n        <notehead>x</notehead>\n        <beam number=\"1\">continue</beam>\n        <beam number=\"2\">begin</beam>\n        </note>\n      <note>\n        <unpitched>\n          <display-step>C</display-step>\n          <display-octave>5</display-octave>\n          </unpitched>\n        <duration>6</duration>\n        <instrument id=\"P1-I1\"/>\n        <voice>1</voice>\n        <type>16th</type>\n        <stem>up</stem>\n        <notehead>diamond</notehead>\n        <beam number=\"1\">end</beam>\n        <beam number=\"2\">end</beam>\n        </note>\n      <note>\n        <unpitched>\n          <display-step>F</display-step>\n          <display-octave>4</display-octave>\n          </unpitched>\n        <duration>12</duration>\n        <instrument id=\"P1-I37\"/>\n        <voice>1</voice>\n        <type>eighth</type>\n        <stem>up</stem>\n        <beam number=\"1\">begin</beam>\n        <notations>\n          <articulations>\n            <accent placement=\"above\"/>\n            </articulations>\n          </notations>\n        </note>\n      <note>\n        <chord/>\n        <unpitched>\n          <display-step>A</display-step>\n          <display-octave>5</display-octave>\n          </unpitched>\n        <duration>12</duration>\n        <instrument id=\"P1-I50\"/>\n        <voice>1</voice>\n        <type>eighth</type>\n        <stem>up</stem>\n        <notehead>x</notehead>\n        </note>\n      <note dynamics=\"71.11\">\n        <unpitched>\n          <display-step>C</display-step>\n          <display-octave>5</display-octave>\n          </unpitched>\n        <duration>12</duration>\n        <instrument id=\"P1-I1\"/>\n        <voice>1</voice>\n        <type>eighth</type>\n        <stem>up</stem>\n        <notehead>diamond</notehead>\n        <beam number=\"1\">end</beam>\n        </note>\n      <note>\n        <chord/>\n        <unpitched>\n          <display-step>A</display-step>\n          <display-octave>5</display-octave>\n          </unpitched>\n        <duration>12</duration>\n        <instrument id=\"P1-I50\"/>\n        <voice>1</voice>\n        <type>eighth</type>\n        <stem>up</stem>\n        <notehead>x</notehead>\n        </note>\n      <note>\n        <unpitched>\n          <display-step>F</display-step>\n          <display-octave>4</display-octave>\n          </unpitched>\n        <duration>6</duration>\n        <instrument id=\"P1-I37\"/>\n        <voice>1</voice>\n        <type>16th</type>\n        <stem>up</stem>\n        <beam number=\"1\">begin</beam>\n        <beam number=\"2\">begin</beam>\n        <notations>\n          <articulations>\n            <accent placement=\"above\"/>\n            </articulations>\n          </notations>\n        </note>\n      <note>\n        <chord/>\n        <unpitched>\n          <display-step>A</display-step>\n          <display-octave>5</display-octave>\n          </unpitched>\n        <duration>6</duration>\n        <instrument id=\"P1-I50\"/>\n        <voice>1</voice>\n        <type>16th</type>\n        <stem>up</stem>\n        <notehead>x</notehead>\n        </note>\n      <note>\n        <unpitched>\n          <display-step>A</display-step>\n          <display-octave>5</display-octave>\n          </unpitched>\n        <duration>6</duration>\n        <instrument id=\"P1-I50\"/>\n        <voice>1</voice>\n        <type>16th</type>\n        <stem>up</stem>\n        <notehead>x</notehead>\n        <beam number=\"1\">continue</beam>\n        <beam number=\"2\">continue</beam>\n        </note>\n      <note>\n        <unpitched>\n          <display-step>C</display-step>\n          <display-octave>5</display-octave>\n          </unpitched>\n        <duration>4</duration>\n        <instrument id=\"P1-I39\"/>\n        <voice>1</voice>\n        <type>16th</type>\n        <time-modification>\n          <actual-notes>3</actual-notes>\n          <normal-notes>2</normal-notes>\n          </time-modification>\n        <stem>up</stem>\n        <beam number=\"1\">continue</beam>\n        <beam number=\"2\">continue</beam>\n        <notations>\n          <tuplet type=\"start\" bracket=\"no\"/>\n          </notations>\n        </note>\n      <note>\n        <unpitched>\n          <display-step>E</display-step>\n          <display-octave>5</display-octave>\n          </unpitched>\n        <duration>4</duration>\n        <instrument id=\"P1-I51\"/>\n        <voice>1</voice>\n        <type>16th</type>\n        <time-modification>\n          <actual-notes>3</actual-notes>\n          <normal-notes>2</normal-notes>\n          </time-modification>\n        <stem>up</stem>\n        <beam number=\"1\">continue</beam>\n        <beam number=\"2\">continue</beam>\n        </note>\n      <note>\n        <unpitched>\n          <display-step>E</display-step>\n          <display-octave>5</display-octave>\n          </unpitched>\n        <duration>4</duration>\n        <instrument id=\"P1-I51\"/>\n        <voice>1</voice>\n        <type>16th</type>\n        <time-modification>\n          <actual-notes>3</actual-notes>\n          <normal-notes>2</normal-notes>\n          </time-modification>\n        <stem>up</stem>\n        <beam number=\"1\">end</beam>\n        <beam number=\"2\">end</beam>\n        <notations>\n          <tuplet type=\"stop\"/>\n          </notations>\n        </note>\n      <note>\n        <unpitched>\n          <display-step>D</display-step>\n          <display-octave>5</display-octave>\n          </unpitched>\n        <duration>4</duration>\n        <instrument id=\"P1-I48\"/>\n        <voice>1</voice>\n        <type>16th</type>\n        <time-modification>\n          <actual-notes>3</actual-notes>\n          <normal-notes>2</normal-notes>\n          </time-modification>\n        <stem>up</stem>\n        <beam number=\"1\">begin</beam>\n        <beam number=\"2\">begin</beam>\n        <notations>\n          <tuplet type=\"start\" bracket=\"no\"/>\n          </notations>\n        </note>\n      <note>\n        <unpitched>\n          <display-step>D</display-step>\n          <display-octave>5</display-octave>\n          </unpitched>\n        <duration>4</duration>\n        <instrument id=\"P1-I48\"/>\n        <voice>1</voice>\n        <type>16th</type>\n        <time-modification>\n          <actual-notes>3</actual-notes>\n          <normal-notes>2</normal-notes>\n          </time-modification>\n        <stem>up</stem>\n        <beam number=\"1\">continue</beam>\n        <beam number=\"2\">continue</beam>\n        </note>\n      <note>\n        <unpitched>\n          <display-step>F</display-step>\n          <display-octave>4</display-octave>\n          </unpitched>\n        <duration>4</duration>\n        <instrument id=\"P1-I37\"/>\n        <voice>1</voice>\n        <type>16th</type>\n        <time-modification>\n          <actual-notes>3</actual-notes>\n          <normal-notes>2</normal-notes>\n          </time-modification>\n        <stem>up</stem>\n        <beam number=\"1\">continue</beam>\n        <beam number=\"2\">continue</beam>\n        <notations>\n          <tuplet type=\"stop\"/>\n          </notations>\n        </note>\n      <note>\n        <unpitched>\n          <display-step>A</display-step>\n          <display-octave>4</display-octave>\n          </unpitched>\n        <duration>4</duration>\n        <instrument id=\"P1-I42\"/>\n        <voice>1</voice>\n        <type>16th</type>\n        <time-modification>\n          <actual-notes>3</actual-notes>\n          <normal-notes>2</normal-notes>\n          </time-modification>\n        <stem>up</stem>\n        <beam number=\"1\">continue</beam>\n        <beam number=\"2\">continue</beam>\n        <notations>\n          <tuplet type=\"start\" bracket=\"no\"/>\n          </notations>\n        </note>\n      <note>\n        <unpitched>\n          <display-step>A</display-step>\n          <display-octave>4</display-octave>\n          </unpitched>\n        <duration>4</duration>\n        <instrument id=\"P1-I42\"/>\n        <voice>1</voice>\n        <type>16th</type>\n        <time-modification>\n          <actual-notes>3</actual-notes>\n          <normal-notes>2</normal-notes>\n          </time-modification>\n        <stem>up</stem>\n        <beam number=\"1\">continue</beam>\n        <beam number=\"2\">continue</beam>\n        </note>\n      <note>\n        <unpitched>\n          <display-step>A</display-step>\n          <display-octave>4</display-octave>\n          </unpitched>\n        <duration>4</duration>\n        <instrument id=\"P1-I42\"/>\n        <voice>1</voice>\n        <type>16th</type>\n        <time-modification>\n          <actual-notes>3</actual-notes>\n          <normal-notes>2</normal-notes>\n          </time-modification>\n        <stem>up</stem>\n        <beam number=\"1\">end</beam>\n        <beam number=\"2\">end</beam>\n        <notations>\n          <tuplet type=\"stop\"/>\n          </notations>\n        </note>\n      </measure>\n    <measure number=\"26\">\n      <note>\n        <rest measure=\"yes\"/>\n        <duration>96</duration>\n        <voice>1</voice>\n        </note>\n      </measure>\n    <measure number=\"27\">\n      <note>\n        <rest measure=\"yes\"/>\n        <duration>96</duration>\n        <voice>1</voice>\n        </note>\n      </measure>\n    <measure number=\"28\">\n      <note>\n        <unpitched>\n          <display-step>F</display-step>\n          <display-octave>4</display-octave>\n          </unpitched>\n        <duration>12</duration>\n        <instrument id=\"P1-I37\"/>\n        <voice>1</voice>\n        <type>eighth</type>\n        <stem>up</stem>\n        <beam number=\"1\">begin</beam>\n        </note>\n      <note>\n        <chord/>\n        <unpitched>\n          <display-step>A</display-step>\n          <display-octave>5</display-octave>\n          </unpitched>\n        <duration>12</duration>\n        <instrument id=\"P1-I50\"/>\n        <voice>1</voice>\n        <type>eighth</type>\n        <stem>up</stem>\n        <notehead>x</notehead>\n        </note>\n      <note>\n        <unpitched>\n          <display-step>F</display-step>\n          <display-octave>4</display-octave>\n          </unpitched>\n        <duration>6</duration>\n        <instrument id=\"P1-I37\"/>\n        <voice>1</voice>\n        <type>16th</type>\n        <stem>up</stem>\n        <beam number=\"1\">continue</beam>\n        <beam number=\"2\">begin</beam>\n        </note>\n      <note>\n        <chord/>\n        <unpitched>\n          <display-step>A</display-step>\n          <display-octave>5</display-octave>\n          </unpitched>\n        <duration>6</duration>\n        <instrument id=\"P1-I50\"/>\n        <voice>1</voice>\n        <type>16th</type>\n        <stem>up</stem>\n        <notehead>x</notehead>\n        </note>\n      <note>\n        <unpitched>\n          <display-step>E</display-step>\n          <display-octave>5</display-octave>\n          </unpitched>\n        <duration>6</duration>\n        <instrument id=\"P1-I51\"/>\n        <voice>1</voice>\n        <type>16th</type>\n        <stem>up</stem>\n        <beam number=\"1\">end</beam>\n        <beam number=\"2\">end</beam>\n        </note>\n      <note>\n        <unpitched>\n          <display-step>F</display-step>\n          <display-octave>4</display-octave>\n          </unpitched>\n        <duration>12</duration>\n        <instrument id=\"P1-I37\"/>\n        <voice>1</voice>\n        <type>eighth</type>\n        <stem>up</stem>\n        <beam number=\"1\">begin</beam>\n        </note>\n      <note>\n        <chord/>\n        <unpitched>\n          <display-step>A</display-step>\n          <display-octave>5</display-octave>\n          </unpitched>\n        <duration>12</duration>\n        <instrument id=\"P1-I50\"/>\n        <voice>1</voice>\n        <type>eighth</type>\n        <stem>up</stem>\n        <notehead>x</notehead>\n        </note>\n      <note>\n        <unpitched>\n          <display-step>F</display-step>\n          <display-octave>4</display-octave>\n          </unpitched>\n        <duration>12</duration>\n        <instrument id=\"P1-I37\"/>\n        <voice>1</voice>\n        <type>eighth</type>\n        <stem>up</stem>\n        <beam number=\"1\">end</beam>\n        </note>\n      <note>\n        <chord/>\n        <unpitched>\n          <display-step>D</display-step>\n          <display-octave>5</display-octave>\n          </unpitched>\n        <duration>12</duration>\n        <instrument id=\"P1-I48\"/>\n        <voice>1</voice>\n        <type>eighth</type>\n        <stem>up</stem>\n        </note>\n      <note>\n        <chord/>\n        <unpitched>\n          <display-step>A</display-step>\n          <display-octave>5</display-octave>\n          </unpitched>\n        <duration>12</duration>\n        <instrument id=\"P1-I50\"/>\n        <voice>1</voice>\n        <type>eighth</type>\n        <stem>up</stem>\n        <notehead>x</notehead>\n        </note>\n      <note>\n        <unpitched>\n          <display-step>F</display-step>\n          <display-octave>4</display-octave>\n          </unpitched>\n        <duration>6</duration>\n        <instrument id=\"P1-I37\"/>\n        <voice>1</voice>\n        <type>16th</type>\n        <stem>up</stem>\n        <beam number=\"1\">begin</beam>\n        <beam number=\"2\">begin</beam>\n        </note>\n      <note>\n        <chord/>\n        <unpitched>\n          <display-step>A</display-step>\n          <display-octave>4</display-octave>\n          </unpitched>\n        <duration>6</duration>\n        <instrument id=\"P1-I42\"/>\n        <voice>1</voice>\n        <type>16th</type>\n        <stem>up</stem>\n        </note>\n      <note>\n        <chord/>\n        <unpitched>\n          <display-step>A</display-step>\n          <display-octave>5</display-octave>\n          </unpitched>\n        <duration>6</duration>\n        <instrument id=\"P1-I50\"/>\n        <voice>1</voice>\n        <type>16th</type>\n        <stem>up</stem>\n        <notehead>x</notehead>\n        </note>\n      <note>\n        <unpitched>\n          <display-step>A</display-step>\n          <display-octave>4</display-octave>\n          </unpitched>\n        <duration>6</duration>\n        <instrument id=\"P1-I42\"/>\n        <voice>1</voice>\n        <type>16th</type>\n        <stem>up</stem>\n        <beam number=\"1\">continue</beam>\n        <beam number=\"2\">end</beam>\n        </note>\n      <note>\n        <unpitched>\n          <display-step>F</display-step>\n          <display-octave>4</display-octave>\n          </unpitched>\n        <duration>12</duration>\n        <instrument id=\"P1-I37\"/>\n        <voice>1</voice>\n        <type>eighth</type>\n        <stem>up</stem>\n        <beam number=\"1\">end</beam>\n        </note>\n      <note>\n        <chord/>\n        <unpitched>\n          <display-step>A</display-step>\n          <display-octave>5</display-octave>\n          </unpitched>\n        <duration>12</duration>\n        <instrument id=\"P1-I50\"/>\n        <voice>1</voice>\n        <type>eighth</type>\n        <stem>up</stem>\n        <notehead>x</notehead>\n        </note>\n      <note>\n        <unpitched>\n          <display-step>F</display-step>\n          <display-octave>4</display-octave>\n          </unpitched>\n        <duration>6</duration>\n        <instrument id=\"P1-I37\"/>\n        <voice>1</voice>\n        <type>16th</type>\n        <stem>up</stem>\n        <beam number=\"1\">begin</beam>\n        <beam number=\"2\">begin</beam>\n        </note>\n      <note>\n        <chord/>\n        <unpitched>\n          <display-step>C</display-step>\n          <display-octave>5</display-octave>\n          </unpitched>\n        <duration>6</duration>\n        <instrument id=\"P1-I39\"/>\n        <voice>1</voice>\n        <type>16th</type>\n        <stem>up</stem>\n        </note>\n      <note>\n        <chord/>\n        <unpitched>\n          <display-step>A</display-step>\n          <display-octave>5</display-octave>\n          </unpitched>\n        <duration>6</duration>\n        <instrument id=\"P1-I50\"/>\n        <voice>1</voice>\n        <type>16th</type>\n        <stem>up</stem>\n        <notehead>x</notehead>\n        </note>\n      <note>\n        <unpitched>\n          <display-step>C</display-step>\n          <display-octave>5</display-octave>\n          </unpitched>\n        <duration>6</duration>\n        <instrument id=\"P1-I39\"/>\n        <voice>1</voice>\n        <type>16th</type>\n        <stem>up</stem>\n        <beam number=\"1\">continue</beam>\n        <beam number=\"2\">continue</beam>\n        </note>\n      <note>\n        <unpitched>\n          <display-step>F</display-step>\n          <display-octave>4</display-octave>\n          </unpitched>\n        <duration>6</duration>\n        <instrument id=\"P1-I37\"/>\n        <voice>1</voice>\n        <type>16th</type>\n        <stem>up</stem>\n        <beam number=\"1\">continue</beam>\n        <beam number=\"2\">continue</beam>\n        </note>\n      <note>\n        <chord/>\n        <unpitched>\n          <display-step>C</display-step>\n          <display-octave>5</display-octave>\n          </unpitched>\n        <duration>6</duration>\n        <instrument id=\"P1-I39\"/>\n        <voice>1</voice>\n        <type>16th</type>\n        <stem>up</stem>\n        </note>\n      <note>\n        <chord/>\n        <unpitched>\n          <display-step>A</display-step>\n          <display-octave>5</display-octave>\n          </unpitched>\n        <duration>6</duration>\n        <instrument id=\"P1-I50\"/>\n        <voice>1</voice>\n        <type>16th</type>\n        <stem>up</stem>\n        <notehead>x</notehead>\n        </note>\n      <note>\n        <unpitched>\n          <display-step>C</display-step>\n          <display-octave>5</display-octave>\n          </unpitched>\n        <duration>6</duration>\n        <instrument id=\"P1-I39\"/>\n        <voice>1</voice>\n        <type>16th</type>\n        <stem>up</stem>\n        <beam number=\"1\">end</beam>\n        <beam number=\"2\">end</beam>\n        </note>\n      </measure>\n    <measure number=\"29\">\n      <note>\n        <rest measure=\"yes\"/>\n        <duration>96</duration>\n        <voice>1</voice>\n        </note>\n      </measure>\n    <measure number=\"30\">\n      <direction placement=\"below\">\n        <direction-type>\n          <wedge type=\"crescendo\" number=\"1\"/>\n          </direction-type>\n        </direction>\n      <note>\n        <unpitched>\n          <display-step>F</display-step>\n          <display-octave>4</display-octave>\n          </unpitched>\n        <duration>6</duration>\n        <instrument id=\"P1-I37\"/>\n        <voice>1</voice>\n        <type>16th</type>\n        <stem>up</stem>\n        <beam number=\"1\">begin</beam>\n        <beam number=\"2\">begin</beam>\n        </note>\n      <note>\n        <chord/>\n        <unpitched>\n          <display-step>C</display-step>\n          <display-octave>5</display-octave>\n          </unpitched>\n        <duration>6</duration>\n        <instrument id=\"P1-I39\"/>\n        <voice>1</voice>\n        <type>16th</type>\n        <stem>up</stem>\n        </note>\n      <note>\n        <chord/>\n        <unpitched>\n          <display-step>A</display-step>\n          <display-octave>5</display-octave>\n          </unpitched>\n        <duration>6</duration>\n        <instrument id=\"P1-I50\"/>\n        <voice>1</voice>\n        <type>16th</type>\n        <stem>up</stem>\n        <notehead>x</notehead>\n        </note>\n      <note>\n        <unpitched>\n          <display-step>C</display-step>\n          <display-octave>5</display-octave>\n          </unpitched>\n        <duration>6</duration>\n        <instrument id=\"P1-I39\"/>\n        <voice>1</voice>\n        <type>16th</type>\n        <stem>up</stem>\n        <beam number=\"1\">continue</beam>\n        <beam number=\"2\">continue</beam>\n        </note>\n      <note>\n        <chord/>\n        <unpitched>\n          <display-step>A</display-step>\n          <display-octave>5</display-octave>\n          </unpitched>\n        <duration>6</duration>\n        <instrument id=\"P1-I50\"/>\n        <voice>1</voice>\n        <type>16th</type>\n        <stem>up</stem>\n        <notehead>x</notehead>\n        </note>\n      <note>\n        <unpitched>\n          <display-step>F</display-step>\n          <display-octave>4</display-octave>\n          </unpitched>\n        <duration>6</duration>\n        <instrument id=\"P1-I37\"/>\n        <voice>1</voice>\n        <type>16th</type>\n        <stem>up</stem>\n        <beam number=\"1\">continue</beam>\n        <beam number=\"2\">continue</beam>\n        </note>\n      <note>\n        <chord/>\n        <unpitched>\n          <display-step>C</display-step>\n          <display-octave>5</display-octave>\n          </unpitched>\n        <duration>6</duration>\n        <instrument id=\"P1-I39\"/>\n        <voice>1</voice>\n        <type>16th</type>\n        <stem>up</stem>\n        </note>\n      <note>\n        <chord/>\n        <unpitched>\n          <display-step>A</display-step>\n          <display-octave>5</display-octave>\n          </unpitched>\n        <duration>6</duration>\n        <instrument id=\"P1-I50\"/>\n        <voice>1</voice>\n        <type>16th</type>\n        <stem>up</stem>\n        <notehead>x</notehead>\n        </note>\n      <note>\n        <unpitched>\n          <display-step>C</display-step>\n          <display-octave>5</display-octave>\n          </unpitched>\n        <duration>6</duration>\n        <instrument id=\"P1-I39\"/>\n        <voice>1</voice>\n        <type>16th</type>\n        <stem>up</stem>\n        <beam number=\"1\">end</beam>\n        <beam number=\"2\">end</beam>\n        </note>\n      <note>\n        <chord/>\n        <unpitched>\n          <display-step>A</display-step>\n          <display-octave>5</display-octave>\n          </unpitched>\n        <duration>6</duration>\n        <instrument id=\"P1-I50\"/>\n        <voice>1</voice>\n        <type>16th</type>\n        <stem>up</stem>\n        <notehead>x</notehead>\n        </note>\n      <note>\n        <unpitched>\n          <display-step>F</display-step>\n          <display-octave>4</display-octave>\n          </unpitched>\n        <duration>6</duration>\n        <instrument id=\"P1-I37\"/>\n        <voice>1</voice>\n        <type>16th</type>\n        <stem>up</stem>\n        <beam number=\"1\">begin</beam>\n        <beam number=\"2\">begin</beam>\n        </note>\n      <note>\n        <chord/>\n        <unpitched>\n          <display-step>C</display-step>\n          <display-octave>5</display-octave>\n          </unpitched>\n        <duration>6</duration>\n        <instrument id=\"P1-I39\"/>\n        <voice>1</voice>\n        <type>16th</type>\n        <stem>up</stem>\n        </note>\n      <note>\n        <chord/>\n        <unpitched>\n          <display-step>A</display-step>\n          <display-octave>5</display-octave>\n          </unpitched>\n        <duration>6</duration>\n        <instrument id=\"P1-I50\"/>\n        <voice>1</voice>\n        <type>16th</type>\n        <stem>up</stem>\n        <notehead>x</notehead>\n        </note>\n      <note>\n        <unpitched>\n          <display-step>C</display-step>\n          <display-octave>5</display-octave>\n          </unpitched>\n        <duration>6</duration>\n        <instrument id=\"P1-I39\"/>\n        <voice>1</voice>\n        <type>16th</type>\n        <stem>up</stem>\n        <beam number=\"1\">continue</beam>\n        <beam number=\"2\">continue</beam>\n        </note>\n      <note>\n        <chord/>\n        <unpitched>\n          <display-step>A</display-step>\n          <display-octave>5</display-octave>\n          </unpitched>\n        <duration>6</duration>\n        <instrument id=\"P1-I50\"/>\n        <voice>1</voice>\n        <type>16th</type>\n        <stem>up</stem>\n        <notehead>x</notehead>\n        </note>\n      <note>\n        <unpitched>\n          <display-step>F</display-step>\n          <display-octave>4</display-octave>\n          </unpitched>\n        <duration>6</duration>\n        <instrument id=\"P1-I37\"/>\n        <voice>1</voice>\n        <type>16th</type>\n        <stem>up</stem>\n        <beam number=\"1\">continue</beam>\n        <beam number=\"2\">continue</beam>\n        </note>\n      <note>\n        <chord/>\n        <unpitched>\n          <display-step>C</display-step>\n          <display-octave>5</display-octave>\n          </unpitched>\n        <duration>6</duration>\n        <instrument id=\"P1-I39\"/>\n        <voice>1</voice>\n        <type>16th</type>\n        <stem>up</stem>\n        </note>\n      <note>\n        <chord/>\n        <unpitched>\n          <display-step>A</display-step>\n          <display-octave>5</display-octave>\n          </unpitched>\n        <duration>6</duration>\n        <instrument id=\"P1-I50\"/>\n        <voice>1</voice>\n        <type>16th</type>\n        <stem>up</stem>\n        <notehead>x</notehead>\n        </note>\n      <note>\n        <unpitched>\n          <display-step>C</display-step>\n          <display-octave>5</display-octave>\n          </unpitched>\n        <duration>6</duration>\n        <instrument id=\"P1-I39\"/>\n        <voice>1</voice>\n        <type>16th</type>\n        <stem>up</stem>\n        <beam number=\"1\">end</beam>\n        <beam number=\"2\">end</beam>\n        </note>\n      <note>\n        <chord/>\n        <unpitched>\n          <display-step>A</display-step>\n          <display-octave>5</display-octave>\n          </unpitched>\n        <duration>6</duration>\n        <instrument id=\"P1-I50\"/>\n        <voice>1</voice>\n        <type>16th</type>\n        <stem>up</stem>\n        <notehead>x</notehead>\n        </note>\n      <note>\n        <unpitched>\n          <display-step>F</display-step>\n          <display-octave>4</display-octave>\n          </unpitched>\n        <duration>6</duration>\n        <instrument id=\"P1-I37\"/>\n        <voice>1</voice>\n        <type>16th</type>\n        <stem>up</stem>\n        <beam number=\"1\">begin</beam>\n        <beam number=\"2\">begin</beam>\n        </note>\n      <note>\n        <chord/>\n        <unpitched>\n          <display-step>C</display-step>\n          <display-octave>5</display-octave>\n          </unpitched>\n        <duration>6</duration>\n        <instrument id=\"P1-I39\"/>\n        <voice>1</voice>\n        <type>16th</type>\n        <stem>up</stem>\n        </note>\n      <note>\n        <chord/>\n        <unpitched>\n          <display-step>A</display-step>\n          <display-octave>5</display-octave>\n          </unpitched>\n        <duration>6</duration>\n        <instrument id=\"P1-I50\"/>\n        <voice>1</voice>\n        <type>16th</type>\n        <stem>up</stem>\n        <notehead>x</notehead>\n        </note>\n      <note>\n        <unpitched>\n          <display-step>C</display-step>\n          <display-octave>5</display-octave>\n          </unpitched>\n        <duration>6</duration>\n        <instrument id=\"P1-I39\"/>\n        <voice>1</voice>\n        <type>16th</type>\n        <stem>up</stem>\n        <beam number=\"1\">continue</beam>\n        <beam number=\"2\">continue</beam>\n        </note>\n      <note>\n        <chord/>\n        <unpitched>\n          <display-step>A</display-step>\n          <display-octave>5</display-octave>\n          </unpitched>\n        <duration>6</duration>\n        <instrument id=\"P1-I50\"/>\n        <voice>1</voice>\n        <type>16th</type>\n        <stem>up</stem>\n        <notehead>x</notehead>\n        </note>\n      <note>\n        <unpitched>\n          <display-step>F</display-step>\n          <display-octave>4</display-octave>\n          </unpitched>\n        <duration>6</duration>\n        <instrument id=\"P1-I37\"/>\n        <voice>1</voice>\n        <type>16th</type>\n        <stem>up</stem>\n        <beam number=\"1\">continue</beam>\n        <beam number=\"2\">continue</beam>\n        </note>\n      <note>\n        <chord/>\n        <unpitched>\n          <display-step>C</display-step>\n          <display-octave>5</display-octave>\n          </unpitched>\n        <duration>6</duration>\n        <instrument id=\"P1-I39\"/>\n        <voice>1</voice>\n        <type>16th</type>\n        <stem>up</stem>\n        </note>\n      <note>\n        <chord/>\n        <unpitched>\n          <display-step>A</display-step>\n          <display-octave>5</display-octave>\n          </unpitched>\n        <duration>6</duration>\n        <instrument id=\"P1-I50\"/>\n        <voice>1</voice>\n        <type>16th</type>\n        <stem>up</stem>\n        <notehead>x</notehead>\n        </note>\n      <note>\n        <unpitched>\n          <display-step>C</display-step>\n          <display-octave>5</display-octave>\n          </unpitched>\n        <duration>6</duration>\n        <instrument id=\"P1-I39\"/>\n        <voice>1</voice>\n        <type>16th</type>\n        <stem>up</stem>\n        <beam number=\"1\">end</beam>\n        <beam number=\"2\">end</beam>\n        </note>\n      <note>\n        <chord/>\n        <unpitched>\n          <display-step>A</display-step>\n          <display-octave>5</display-octave>\n          </unpitched>\n        <duration>6</duration>\n        <instrument id=\"P1-I50\"/>\n        <voice>1</voice>\n        <type>16th</type>\n        <stem>up</stem>\n        <notehead>x</notehead>\n        </note>\n      <note>\n        <unpitched>\n          <display-step>F</display-step>\n          <display-octave>4</display-octave>\n          </unpitched>\n        <duration>6</duration>\n        <instrument id=\"P1-I37\"/>\n        <voice>1</voice>\n        <type>16th</type>\n        <stem>up</stem>\n        <beam number=\"1\">begin</beam>\n        <beam number=\"2\">begin</beam>\n        </note>\n      <note>\n        <chord/>\n        <unpitched>\n          <display-step>C</display-step>\n          <display-octave>5</display-octave>\n          </unpitched>\n        <duration>6</duration>\n        <instrument id=\"P1-I39\"/>\n        <voice>1</voice>\n        <type>16th</type>\n        <stem>up</stem>\n        </note>\n      <note>\n        <chord/>\n        <unpitched>\n          <display-step>A</display-step>\n          <display-octave>5</display-octave>\n          </unpitched>\n        <duration>6</duration>\n        <instrument id=\"P1-I50\"/>\n        <voice>1</voice>\n        <type>16th</type>\n        <stem>up</stem>\n        <notehead>x</notehead>\n        </note>\n      <note>\n        <unpitched>\n          <display-step>C</display-step>\n          <display-octave>5</display-octave>\n          </unpitched>\n        <duration>6</duration>\n        <instrument id=\"P1-I39\"/>\n        <voice>1</voice>\n        <type>16th</type>\n        <stem>up</stem>\n        <beam number=\"1\">continue</beam>\n        <beam number=\"2\">continue</beam>\n        </note>\n      <note>\n        <chord/>\n        <unpitched>\n          <display-step>A</display-step>\n          <display-octave>5</display-octave>\n          </unpitched>\n        <duration>6</duration>\n        <instrument id=\"P1-I50\"/>\n        <voice>1</voice>\n        <type>16th</type>\n        <stem>up</stem>\n        <notehead>x</notehead>\n        </note>\n      <note>\n        <unpitched>\n          <display-step>F</display-step>\n          <display-octave>4</display-octave>\n          </unpitched>\n        <duration>6</duration>\n        <instrument id=\"P1-I37\"/>\n        <voice>1</voice>\n        <type>16th</type>\n        <stem>up</stem>\n        <beam number=\"1\">continue</beam>\n        <beam number=\"2\">continue</beam>\n        </note>\n      <note>\n        <chord/>\n        <unpitched>\n          <display-step>C</display-step>\n          <display-octave>5</display-octave>\n          </unpitched>\n        <duration>6</duration>\n        <instrument id=\"P1-I39\"/>\n        <voice>1</voice>\n        <type>16th</type>\n        <stem>up</stem>\n        </note>\n      <note>\n        <chord/>\n        <unpitched>\n          <display-step>A</display-step>\n          <display-octave>5</display-octave>\n          </unpitched>\n        <duration>6</duration>\n        <instrument id=\"P1-I50\"/>\n        <voice>1</voice>\n        <type>16th</type>\n        <stem>up</stem>\n        <notehead>x</notehead>\n        </note>\n      <note>\n        <unpitched>\n          <display-step>C</display-step>\n          <display-octave>5</display-octave>\n          </unpitched>\n        <duration>6</duration>\n        <instrument id=\"P1-I39\"/>\n        <voice>1</voice>\n        <type>16th</type>\n        <stem>up</stem>\n        <beam number=\"1\">end</beam>\n        <beam number=\"2\">end</beam>\n        </note>\n      <note>\n        <chord/>\n        <unpitched>\n          <display-step>A</display-step>\n          <display-octave>5</display-octave>\n          </unpitched>\n        <duration>6</duration>\n        <instrument id=\"P1-I50\"/>\n        <voice>1</voice>\n        <type>16th</type>\n        <stem>up</stem>\n        <notehead>x</notehead>\n        </note>\n      <direction placement=\"below\">\n        <direction-type>\n          <wedge type=\"stop\" number=\"1\"/>\n          </direction-type>\n        </direction>\n      <barline location=\"right\">\n        <bar-style>light-heavy</bar-style>\n        </barline>\n      </measure>\n    </part>\n  </score-partwise>\n",
  "sections": [
    {
      "id": "mr167edbnjvna",
      "name": "Introdução",
      "marks": [
        {
          "id": "mr167sg78kx0s",
          "groove": "g1",
          "lyrics": "[metrônomo + bateria]",
          "measureStart": 3,
          "measureEnd": 4
        }
      ]
    },
    {
      "id": "mr15v6lnfin27",
      "name": "Estrofe 1",
      "marks": [
        {
          "id": "mr15zj2tl82eo",
          "groove": "nd",
          "lyrics": "[swell] As muitas gerações rendidas em louvor\nCantando ao Cordeiro uma canção\nOs que em Ti se foram e os que hão de crer\nCantando ao Cordeiro uma canção"
        }
      ]
    },
    {
      "id": "mr15xeqpfsa8z",
      "name": "Pré-refrão",
      "marks": [
        {
          "id": "mr15zv7ro2prx",
          "groove": "g2",
          "lyrics": "[swell] Teu nome é o mais alto\nTeu nome é o maior\nTeu nome é sobre todos\nOs tronos e domínios, governos e poderes\nTeu nome é sobre todos",
          "measureStart": 9
        }
      ]
    },
    {
      "id": "mr15xqpnxrtnl",
      "name": "Refrão",
      "marks": [
        {
          "id": "mr15zxrxzqk0l",
          "groove": "g2",
          "lyrics": "E os anjos [swell] clamam: Santo",
          "measureStart": 9
        },
        {
          "id": "mr1603broppx9",
          "groove": "g3",
          "lyrics": "Toda criação: Santo\nExaltado és: Santo\nSanto pra",
          "measureStart": 11
        },
        {
          "id": "mr160adfaqzgr",
          "groove": "g4",
          "lyrics": "sempre",
          "measureStart": 13,
          "measureEnd": 14
        }
      ]
    },
    {
      "id": "mr15ym4fcwfr9",
      "name": "Estrofe 2",
      "marks": [
        {
          "id": "mr160fnp6ktx8",
          "groove": "g5",
          "lyrics": "[swell] Quem foi perdoado e redimido foi\nCante ao Cordeiro uma canção\nAquele que é livre e leva o Seu nome\nCante ao Cordeiro uma canção",
          "measureStart": 17
        },
        {
          "id": "mr160klplguy5",
          "groove": "nd",
          "lyrics": "Cantaremos para sempre, amém [virada]"
        }
      ]
    },
    {
      "id": "mr15ytrfjc7cr",
      "name": "Refrão",
      "marks": [
        {
          "id": "mr160yyvhg58y",
          "groove": "g6",
          "lyrics": "E os anjos clamam: Santo\nToda criação: Santo\nExaltado és: Santo\nSanto pra sempre\n\nO Teu povo canta: Santo\nSim, ao Rei dos reis: Santo\nTu sempre serás Santo\nSanto pra sempre [down]",
          "measureStart": 20
        }
      ]
    },
    {
      "id": "mr15z5htcn17r",
      "name": "Pré-refrão",
      "marks": [
        {
          "id": "mr1615eezwql7",
          "groove": "g5",
          "lyrics": "Teu nome é o mais alto\nTeu nome é o maior\nTeu nome é sobre todos\nOs tronos e domínios, governos e poderes\nTeu nome é sobre",
          "measureStart": 17
        },
        {
          "id": "mr1616ojkf1q8",
          "groove": "g7",
          "lyrics": "todos",
          "measureStart": 23
        }
      ]
    },
    {
      "id": "mr161oyxl2c1w",
      "name": "Pré-refrão",
      "marks": [
        {
          "id": "mr161oyxzeymo",
          "groove": "g8",
          "lyrics": "Teu nome é o mais alto\nTeu nome é o maior\nTeu nome é sobre todos [up]",
          "measureStart": 24,
          "measureEnd": 25
        },
        {
          "id": "mr161oyx4nqsg",
          "groove": "g9",
          "lyrics": "Os tronos e domínios, governos e poderes\nTeu nome é sobre [virada + swell]",
          "measureStart": 28
        },
        {
          "id": "mr16267jgs1ht",
          "groove": "g10",
          "lyrics": "todos",
          "measureStart": 30
        }
      ]
    },
    {
      "id": "mr15zc2fzg4yt",
      "name": "Refrão",
      "marks": [
        {
          "id": "mr162fphn89fq",
          "groove": "g6",
          "lyrics": "E os anjos clamam: Santo\nToda criação: Santo\nExaltado és: Santo\nSanto pra sempre [virada + swell]\n\nO Teu povo canta: Santo\nSim, ao Rei dos reis: Santo\nTu sempre serás Santo\nSanto pra sempre\n\nTu sempre",
          "measureStart": 20
        },
        {
          "id": "mr162h85np9q5",
          "groove": "nd",
          "lyrics": "serás Santo\nSanto pra sempre"
        }
      ]
    }
  ],
  "id": "mr16cj7dw6wfm",
  "createdAt": 1782855861817,
  "updatedAt": 1782934600162
}